pyrtout/__init__.py
pyrtout/exceptions.py
pyrtout/timeout.py
pyrtout-1.0.5.dist-info/LICENSE
pyrtout-1.0.5.dist-info/METADATA
pyrtout-1.0.5.dist-info/WHEEL
pyrtout-1.0.5.dist-info/top_level.txt
pyrtout-1.0.5.dist-info/RECORD
