Metadata-Version: 2.1
Name: pyrtout
Version: 1.0.5
Summary: Timeout & retry functions in Python with a single line of code
Home-page: UNKNOWN
Author: Arijit Roy (radioactive11)
Author-email: <roy.arijit@icloud.com>
License: UNKNOWN
Platform: UNKNOWN
